tensorflow_nufft-0.12.0.dist-info/top_level.txt
tensorflow_nufft-0.12.0.dist-info/METADATA
tensorflow_nufft-0.12.0.dist-info/LICENSE
tensorflow_nufft-0.12.0.dist-info/RECORD
tensorflow_nufft-0.12.0.dist-info/WHEEL
tensorflow_nufft/__init__.py
tensorflow_nufft/__about__.py
tensorflow_nufft/python/__init__.py
tensorflow_nufft/python/ops/nufft_ops.py
tensorflow_nufft/python/ops/_nufft_ops.so
tensorflow_nufft/python/ops/__init__.py
tensorflow_nufft/python/ops/nufft_options.py
tensorflow_nufft/proto/nufft_options_pb2.py
tensorflow_nufft/proto/__init__.py
tensorflow_nufft.libs/libgomp-b6de5f8b.so.1.0.0
