Metadata-Version: 2.1
Name: tensorflow-nufft
Version: 0.12.0
Summary: A fast, native non-uniform FFT op for TensorFlow.
Home-page: https://github.com/mrphys/tensorflow-nufft
Author: Javier Montalt Tordera
Author-email: javier.montalt@outlook.com
License: Apache 2.0
Keywords: tensorflow,nufft,ml
Classifier: Development Status :: 4 - Beta
Classifier: Environment :: GPU
Classifier: Environment :: GPU :: NVIDIA CUDA
Classifier: Intended Audience :: Developers
Classifier: Intended Audience :: Science/Research
Classifier: License :: OSI Approved :: Apache Software License
Classifier: Operating System :: OS Independent
Classifier: Programming Language :: C++
Classifier: Programming Language :: Python :: 3
Classifier: Programming Language :: Python :: 3.7
Classifier: Programming Language :: Python :: 3.8
Classifier: Programming Language :: Python :: 3.9
Classifier: Topic :: Scientific/Engineering :: Mathematics
Classifier: Topic :: Software Development :: Libraries
Classifier: Topic :: Software Development :: Libraries :: Python Modules
License-File: LICENSE
Requires-Dist: packaging
Requires-Dist: pydantic
Requires-Dist: tensorflow (<2.12.0,>=2.11.0)
